relativeimport/__init__.py
relativeimport-99.0.6.dist-info/LICENSE
relativeimport-99.0.6.dist-info/METADATA
relativeimport-99.0.6.dist-info/WHEEL
relativeimport-99.0.6.dist-info/top_level.txt
relativeimport-99.0.6.dist-info/RECORD
