Metadata-Version: 2.1
Name: relativeimport
Version: 99.0.6
Summary: do shorter code to import from relative path
Home-page: UNKNOWN
Author: ltaoist
Author-email: ltaoist@163.com.com
License: BSD License
Platform: all
Classifier: Intended Audience :: Developers
Classifier: Operating System :: OS Independent
Classifier: Programming Language :: Python
License-File: LICENSE
